<?xml version='1.0' encoding='UTF-8' standalone='yes' ?><hierarchy rotation="0"><node index="0" text="" resource-id="" class="android.widget.FrameLayout" package="com.yourprime.app" content-desc="" checkable="false" checked="false" clickable="false" enabled="true" focusable="false" focused="false" scrollable="false" long-clickable="false" password="false" selected="false" bounds="[0,0][1344,2992]" drawing-order="0" hint=""><node index="0" text="" resource-id="" class="android.widget.LinearLayout" package="com.yourprime.app" content-desc="" checkable="false" checked="false" clickable="false" enabled="true" focusable="false" focused="false" scrollable="false" long-clickable="false" password="false" selected="false" bounds="[0,0][1344,2992]" drawing-order="1" hint=""><node index="0" text="" resource-id="" class="android.widget.FrameLayout" package="com.yourprime.app" content-desc="" checkable="false" checked="false" clickable="false" enabled="true" focusable="false" focused="false" scrollable="false" long-clickable="false" password="false" selected="false" bounds="[0,0][1344,2992]" drawing-order="2" hint=""><node index="0" text="" resource-id="com.yourprime.app:id/action_bar_root" class="android.widget.LinearLayout" package="com.yourprime.app" content-desc="" checkable="false" checked="false" clickable="false" enabled="true" focusable="false" focused="false" scrollable="false" long-clickable="false" password="false" selected="false" bounds="[0,0][1344,2992]" drawing-order="1" hint=""><node index="0" text="" resource-id="android:id/content" class="android.widget.FrameLayout" package="com.yourprime.app" content-desc="" checkable="false" checked="false" clickable="false" enabled="true" focusable="false" focused="false" scrollable="false" long-clickable="false" password="false" selected="false" bounds="[0,0][1344,2992]" drawing-order="2" hint=""><node index="0" text="" resource-id="" class="android.widget.FrameLayout" package="com.yourprime.app" content-desc="" checkable="false" checked="false" clickable="false" enabled="true" focusable="false" focused="false" scrollable="false" long-clickable="false" password="false" selected="false" bounds="[0,0][1344,2992]" drawing-order="1" hint=""><node index="0" text="" resource-id="" class="android.view.ViewGroup" package="com.yourprime.app" content-desc="" checkable="false" checked="false" clickable="false" enabled="true" focusable="false" focused="false" scrollable="false" long-clickable="false" password="false" selected="false" bounds="[0,0][1344,2992]" drawing-order="1" hint=""><node index="0" text="" resource-id="" class="android.view.ViewGroup" package="com.yourprime.app" content-desc="" checkable="false" checked="false" clickable="false" enabled="true" focusable="false" focused="false" scrollable="false" long-clickable="false" password="false" selected="false" bounds="[0,0][1344,2992]" drawing-order="1" hint=""><node index="0" text="" resource-id="" class="android.view.ViewGroup" package="com.yourprime.app" content-desc="" checkable="false" checked="false" clickable="false" enabled="true" focusable="false" focused="false" scrollable="false" long-clickable="false" password="false" selected="false" bounds="[0,0][1344,2776]" drawing-order="1" hint=""><node index="0" text="" resource-id="" class="android.widget.FrameLayout" package="com.yourprime.app" content-desc="" checkable="false" checked="false" clickable="false" enabled="true" focusable="false" focused="false" scrollable="false" long-clickable="false" password="false" selected="false" bounds="[0,0][1344,2776]" drawing-order="1" hint=""><node index="0" text="" resource-id="" class="android.view.ViewGroup" package="com.yourprime.app" content-desc="" checkable="false" checked="false" clickable="false" enabled="true" focusable="false" focused="false" scrollable="false" long-clickable="false" password="false" selected="false" bounds="[0,0][1344,2776]" drawing-order="1" hint=""><node index="0" text="" resource-id="" class="android.view.ViewGroup" package="com.yourprime.app" content-desc="" checkable="false" checked="false" clickable="false" enabled="true" focusable="false" focused="false" scrollable="false" long-clickable="false" password="false" selected="false" bounds="[0,0][1344,2776]" drawing-order="1" hint=""><node index="0" text="" resource-id="" class="android.view.ViewGroup" package="com.yourprime.app" content-desc="" checkable="false" checked="false" clickable="false" enabled="true" focusable="false" focused="false" scrollable="false" long-clickable="false" password="false" selected="false" bounds="[0,0][1344,2776]" drawing-order="1" hint=""><node index="0" text="" resource-id="" class="android.widget.ScrollView" package="com.yourprime.app" content-desc="" checkable="false" checked="false" clickable="false" enabled="true" focusable="true" focused="false" scrollable="true" long-clickable="false" password="false" selected="false" bounds="[0,159][1344,2704]" drawing-order="1" hint=""><node index="0" text="" resource-id="" class="android.view.ViewGroup" package="com.yourprime.app" content-desc="" checkable="false" checked="false" clickable="false" enabled="true" focusable="false" focused="false" scrollable="false" long-clickable="false" password="false" selected="false" bounds="[0,159][1344,2704]" drawing-order="1" hint=""><node index="16" text="" resource-id="" class="android.view.ViewGroup" package="com.yourprime.app" content-desc="" checkable="false" checked="false" clickable="false" enabled="true" focusable="false" focused="false" scrollable="false" long-clickable="false" password="false" selected="false" bounds="[60,159][1284,270]" drawing-order="17" hint="" /><node index="17" text="RECUPERACION" resource-id="" class="android.widget.TextView" package="com.yourprime.app" content-desc="" checkable="false" checked="false" clickable="false" enabled="true" focusable="false" focused="false" scrollable="false" long-clickable="false" password="false" selected="false" bounds="[105,159][1239,35]" drawing-order="18" hint="" /><node index="18" text="0%" resource-id="" class="android.widget.TextView" package="com.yourprime.app" content-desc="" checkable="false" checked="false" clickable="false" enabled="true" focusable="false" focused="false" scrollable="false" long-clickable="false" password="false" selected="false" bounds="[105,159][1239,150]" drawing-order="19" hint="" /><node index="19" text="Sin lectura suficiente todavia" resource-id="" class="android.widget.TextView" package="com.yourprime.app" content-desc="" checkable="false" checked="false" clickable="false" enabled="true" focusable="false" focused="false" scrollable="false" long-clickable="false" password="false" selected="false" bounds="[105,171][1239,224]" drawing-order="20" hint="" /><node index="20" text="" resource-id="" class="android.view.ViewGroup" package="com.yourprime.app" content-desc="" checkable="false" checked="false" clickable="false" enabled="true" focusable="false" focused="false" scrollable="false" long-clickable="false" password="false" selected="false" bounds="[60,312][1284,906]" drawing-order="21" hint="" /><node index="21" text="PROXIMA SESION" resource-id="" class="android.widget.TextView" package="com.yourprime.app" content-desc="" checkable="false" checked="false" clickable="false" enabled="true" focusable="false" focused="false" scrollable="false" long-clickable="false" password="false" selected="false" bounds="[105,367][1239,420]" drawing-order="22" hint="" /><node index="22" text="Sin sesion proxima" resource-id="" class="android.widget.TextView" package="com.yourprime.app" content-desc="" checkable="false" checked="false" clickable="false" enabled="true" focusable="false" focused="false" scrollable="false" long-clickable="false" password="false" selected="false" bounds="[105,452][1239,536]" drawing-order="23" hint="" /><node index="23" text="Cuando migremos o actives un programa, aqui vas a ver tu proxima sesion." resource-id="" class="android.widget.TextView" package="com.yourprime.app" content-desc="" checkable="false" checked="false" clickable="false" enabled="true" focusable="false" focused="false" scrollable="false" long-clickable="false" password="false" selected="false" bounds="[105,557][1239,683]" drawing-order="24" hint="" /><node index="24" text="" resource-id="" class="android.widget.Button" package="com.yourprime.app" content-desc="Ver progreso" checkable="false" checked="false" clickable="true" enabled="true" focusable="true" focused="false" scrollable="false" long-clickable="false" password="false" selected="false" bounds="[105,725][1239,851]" drawing-order="25" hint=""><node index="0" text="Ver progreso" resource-id="" class="android.widget.TextView" package="com.yourprime.app" content-desc="" checkable="false" checked="false" clickable="false" enabled="true" focusable="false" focused="false" scrollable="false" long-clickable="false" password="false" selected="false" bounds="[549,756][794,819]" drawing-order="1" hint="" /></node><node index="25" text="" resource-id="" class="android.view.ViewGroup" package="com.yourprime.app" content-desc="" checkable="false" checked="false" clickable="false" enabled="true" focusable="false" focused="false" scrollable="false" long-clickable="false" password="false" selected="false" bounds="[60,948][1284,1479]" drawing-order="26" hint="" /><node index="26" text="RECORDATORIOS" resource-id="" class="android.widget.TextView" package="com.yourprime.app" content-desc="" checkable="false" checked="false" clickable="false" enabled="true" focusable="false" focused="false" scrollable="false" long-clickable="false" password="false" selected="false" bounds="[105,1003][1239,1056]" drawing-order="27" hint="" /><node index="27" text="Entreno 18:00" resource-id="" class="android.widget.TextView" package="com.yourprime.app" content-desc="" checkable="false" checked="false" clickable="false" enabled="true" focusable="false" focused="false" scrollable="false" long-clickable="false" password="false" selected="false" bounds="[105,1088][1239,1172]" drawing-order="28" hint="" /><node index="28" text="Recordatorios de comida apagados" resource-id="" class="android.widget.TextView" package="com.yourprime.app" content-desc="" checkable="false" checked="false" clickable="false" enabled="true" focusable="false" focused="false" scrollable="false" long-clickable="false" password="false" selected="false" bounds="[105,1193][1239,1256]" drawing-order="29" hint="" /><node index="29" text="" resource-id="" class="android.widget.Button" package="com.yourprime.app" content-desc="Abrir ajustes" checkable="false" checked="false" clickable="true" enabled="true" focusable="true" focused="false" scrollable="false" long-clickable="false" password="false" selected="false" bounds="[105,1298][1239,1424]" drawing-order="30" hint=""><node index="0" text="Abrir ajustes" resource-id="" class="android.widget.TextView" package="com.yourprime.app" content-desc="" checkable="false" checked="false" clickable="false" enabled="true" focusable="false" focused="false" scrollable="false" long-clickable="false" password="false" selected="false" bounds="[551,1329][792,1392]" drawing-order="1" hint="" /></node><node index="30" text="" resource-id="" class="android.view.ViewGroup" package="com.yourprime.app" content-desc="" checkable="false" checked="false" clickable="false" enabled="true" focusable="false" focused="false" scrollable="false" long-clickable="false" password="false" selected="false" bounds="[60,1521][1284,2116]" drawing-order="31" hint="" /><node index="31" text="BIENESTAR" resource-id="" class="android.widget.TextView" package="com.yourprime.app" content-desc="" checkable="false" checked="false" clickable="false" enabled="true" focusable="false" focused="false" scrollable="false" long-clickable="false" password="false" selected="false" bounds="[105,1576][1239,1629]" drawing-order="32" hint="" /><node index="32" text="Sin sueno importado todavia" resource-id="" class="android.widget.TextView" package="com.yourprime.app" content-desc="" checkable="false" checked="false" clickable="false" enabled="true" focusable="false" focused="false" scrollable="false" long-clickable="false" password="false" selected="false" bounds="[105,1661][1239,1745]" drawing-order="33" hint="" /><node index="33" text="Cuando wellbeing tenga datos útiles en RN, aquí resumiremos descanso, agua y tareas pendientes." resource-id="" class="android.widget.TextView" package="com.yourprime.app" content-desc="" checkable="false" checked="false" clickable="false" enabled="true" focusable="false" focused="false" scrollable="false" long-clickable="false" password="false" selected="false" bounds="[105,1766][1239,1892]" drawing-order="34" hint="" /><node index="34" text="" resource-id="" class="android.widget.Button" package="com.yourprime.app" content-desc="Ver progreso" checkable="false" checked="false" clickable="true" enabled="true" focusable="true" focused="false" scrollable="false" long-clickable="false" password="false" selected="false" bounds="[105,1934][1239,2060]" drawing-order="35" hint=""><node index="0" text="Ver progreso" resource-id="" class="android.widget.TextView" package="com.yourprime.app" content-desc="" checkable="false" checked="false" clickable="false" enabled="true" focusable="false" focused="false" scrollable="false" long-clickable="false" password="false" selected="false" bounds="[549,1965][794,2028]" drawing-order="1" hint="" /></node><node index="35" text="" resource-id="" class="android.view.ViewGroup" package="com.yourprime.app" content-desc="" checkable="false" checked="false" clickable="false" enabled="true" focusable="false" focused="false" scrollable="false" long-clickable="false" password="false" selected="false" bounds="[60,2158][1284,2584]" drawing-order="36" hint="" /><node index="36" text="TU BASE" resource-id="" class="android.widget.TextView" package="com.yourprime.app" content-desc="" checkable="false" checked="false" clickable="false" enabled="true" focusable="false" focused="false" scrollable="false" long-clickable="false" password="false" selected="false" bounds="[105,2213][1239,2266]" drawing-order="37" hint="" /><node index="37" text="Base nueva preparada" resource-id="" class="android.widget.TextView" package="com.yourprime.app" content-desc="" checkable="false" checked="false" clickable="false" enabled="true" focusable="false" focused="false" scrollable="false" long-clickable="false" password="false" selected="false" bounds="[105,2298][1239,2382]" drawing-order="38" hint="" /><node index="38" text="Seguimos listos para recibir tus datos locales cuando hagamos el relevo completo desde la app anterior." resource-id="" class="android.widget.TextView" package="com.yourprime.app" content-desc="" checkable="false" checked="false" clickable="false" enabled="true" focusable="false" focused="false" scrollable="false" long-clickable="false" password="false" selected="false" bounds="[105,2403][1239,2529]" drawing-order="39" hint="" /></node></node></node></node></node></node></node><node index="1" text="" resource-id="" class="android.view.ViewGroup" package="com.yourprime.app" content-desc="" checkable="false" checked="false" clickable="false" enabled="true" focusable="false" focused="false" scrollable="false" long-clickable="false" password="false" selected="false" bounds="[0,2776][1344,2992]" drawing-order="2" hint=""><node index="0" text="" resource-id="" class="android.view.ViewGroup" package="com.yourprime.app" content-desc="" checkable="false" checked="false" clickable="false" enabled="true" focusable="false" focused="false" scrollable="false" long-clickable="false" password="false" selected="false" bounds="[0,2777][1344,2992]" drawing-order="1" hint="" /><node index="1" text="" resource-id="" class="android.view.View" package="com.yourprime.app" content-desc="⏷, Inicio" checkable="false" checked="false" clickable="true" enabled="true" focusable="true" focused="false" scrollable="false" long-clickable="false" password="false" selected="true" bounds="[0,2801][269,2962]" drawing-order="2" hint=""><node index="1" text="⏷" resource-id="" class="android.widget.TextView" package="com.yourprime.app" content-desc="" checkable="false" checked="false" clickable="false" enabled="true" focusable="false" focused="false" scrollable="false" long-clickable="false" password="false" selected="false" bounds="[118,2816][151,2900]" drawing-order="1" hint="" /><node index="2" text="Inicio" resource-id="" class="android.widget.TextView" package="com.yourprime.app" content-desc="" checkable="false" checked="false" clickable="false" enabled="true" focusable="false" focused="false" scrollable="false" long-clickable="false" password="false" selected="false" bounds="[90,2900][178,2949]" drawing-order="3" hint="" /></node><node index="2" text="" resource-id="" class="android.view.View" package="com.yourprime.app" content-desc="⏷, Entreno" checkable="false" checked="false" clickable="true" enabled="true" focusable="true" focused="false" scrollable="false" long-clickable="false" password="false" selected="false" bounds="[269,2801][538,2962]" drawing-order="3" hint=""><node index="1" text="⏷" resource-id="" class="android.widget.TextView" package="com.yourprime.app" content-desc="" checkable="false" checked="false" clickable="false" enabled="true" focusable="false" focused="false" scrollable="false" long-clickable="false" password="false" selected="false" bounds="[387,2816][420,2900]" drawing-order="2" hint="" /><node index="2" text="Entreno" resource-id="" class="android.widget.TextView" package="com.yourprime.app" content-desc="" checkable="false" checked="false" clickable="false" enabled="true" focusable="false" focused="false" scrollable="false" long-clickable="false" password="false" selected="false" bounds="[341,2900][465,2949]" drawing-order="3" hint="" /></node><node index="3" text="" resource-id="" class="android.view.View" package="com.yourprime.app" content-desc="⏷, Nutrición" checkable="false" checked="false" clickable="true" enabled="true" focusable="true" focused="false" scrollable="false" long-clickable="false" password="false" selected="false" bounds="[538,2801][806,2962]" drawing-order="4" hint=""><node index="1" text="⏷" resource-id="" class="android.widget.TextView" package="com.yourprime.app" content-desc="" checkable="false" checked="false" clickable="false" enabled="true" focusable="false" focused="false" scrollable="false" long-clickable="false" password="false" selected="false" bounds="[656,2816][689,2900]" drawing-order="2" hint="" /><node index="2" text="Nutrición" resource-id="" class="android.widget.TextView" package="com.yourprime.app" content-desc="" checkable="false" checked="false" clickable="false" enabled="true" focusable="false" focused="false" scrollable="false" long-clickable="false" password="false" selected="false" bounds="[598,2900][746,2949]" drawing-order="3" hint="" /></node><node index="4" text="" resource-id="" class="android.view.View" package="com.yourprime.app" content-desc="⏷, Progreso" checkable="false" checked="false" clickable="true" enabled="true" focusable="true" focused="false" scrollable="false" long-clickable="false" password="false" selected="false" bounds="[806,2801][1075,2962]" drawing-order="5" hint=""><node index="1" text="⏷" resource-id="" class="android.widget.TextView" package="com.yourprime.app" content-desc="" checkable="false" checked="false" clickable="false" enabled="true" focusable="false" focused="false" scrollable="false" long-clickable="false" password="false" selected="false" bounds="[924,2816][957,2900]" drawing-order="2" hint="" /><node index="2" text="Progreso" resource-id="" class="android.widget.TextView" package="com.yourprime.app" content-desc="" checkable="false" checked="false" clickable="false" enabled="true" focusable="false" focused="false" scrollable="false" long-clickable="false" password="false" selected="false" bounds="[866,2900][1013,2949]" drawing-order="3" hint="" /></node><node index="5" text="" resource-id="" class="android.view.View" package="com.yourprime.app" content-desc="⏷, Ajustes" checkable="false" checked="false" clickable="true" enabled="true" focusable="true" focused="false" scrollable="false" long-clickable="false" password="false" selected="false" bounds="[1075,2801][1344,2962]" drawing-order="6" hint=""><node index="1" text="⏷" resource-id="" class="android.widget.TextView" package="com.yourprime.app" content-desc="" checkable="false" checked="false" clickable="false" enabled="true" focusable="false" focused="false" scrollable="false" long-clickable="false" password="false" selected="false" bounds="[1193,2816][1226,2900]" drawing-order="2" hint="" /><node index="2" text="Ajustes" resource-id="" class="android.widget.TextView" package="com.yourprime.app" content-desc="" checkable="false" checked="false" clickable="false" enabled="true" focusable="false" focused="false" scrollable="false" long-clickable="false" password="false" selected="false" bounds="[1148,2900][1269,2949]" drawing-order="3" hint="" /></node></node></node></node></node></node></node></node></node></node></hierarchy>
